README.txt
setup.py
pg_pybench/__init__.py
pg_pybench/cpu_load.py
pg_pybench/executeSql.py
pg_pybench/formTestQuery.py
pg_pybench/initdbSql.py
pg_pybench/io_count.py
pg_pybench/performTests.py
pg_pybench/pyBench.py
pg_pybench/utilfunc.py
pg_pybench.egg-info/PKG-INFO
pg_pybench.egg-info/SOURCES.txt
pg_pybench.egg-info/dependency_links.txt
pg_pybench.egg-info/not-zip-safe
pg_pybench.egg-info/requires.txt
pg_pybench.egg-info/top_level.txt