Metadata-Version: 1.1
Name: pg-pybench
Version: 1.6
Summary: PostgreSQL benchmarking
Home-page: https://github.com/rugging24/pg_pybench
Author: Olakunle Olaniyi
Author-email: rugging24@gmail.com
License: PostgreSQL License
Platform: UNKNOWN
Classifier: Development Status :: 3 - Alpha
Classifier: License :: OSI Approved :: MIT License
Classifier: Programming Language :: Python :: 2.7
Classifier: Topic :: System :: Benchmark
